setup.py
revotool/__init__.py
revotool/common.py
revotool/fs.py
revotool/modx.py
revotool/pull.py
revotool/push.py
revotool.egg-info/PKG-INFO
revotool.egg-info/SOURCES.txt
revotool.egg-info/dependency_links.txt
revotool.egg-info/not-zip-safe
revotool.egg-info/requires.txt
revotool.egg-info/top_level.txt
scripts/revotool