Metadata-Version: 1.1
Name: revotool
Version: 0.1.0
Summary: Revotool is a CLI tool for working with MODX Revolution™
Home-page: https://github.com/myfreeweb/revotool
Author: Greg V
Author-email: floatboth@me.com
License: Apache License 2.0
Keywords: revotool
Platform: UNKNOWN
Classifier: Development Status :: 2 - Pre-Alpha
Classifier: Intended Audience :: Developers
Classifier: License :: OSI Approved :: Apache Software License
Classifier: Natural Language :: English
Classifier: Programming Language :: Python :: 2
Classifier: Programming Language :: Python :: 2.7
Classifier: Programming Language :: Python :: 3
Classifier: Programming Language :: Python :: 3.3
